{
  "last_index": 0,
  "email_sent_log": {
    "abhishek.bansode@charcoaleats.com": "2026-01-01T05:01:16.040680",
    "abhishek.nirmal@charcoaleats.com": "2026-01-01T05:01:16.040680",
    "akash.yadav@charcoaleats.com": "2026-01-01T05:01:16.040680",
    "areez@charcoaleats.com": "2026-01-01T11:40:33.888915",
    "ashishyedke92@gmail.com": "2026-01-01T11:40:33.888915",
    "ataullah.khan@charcoaleats.com": "2026-01-01T11:40:33.888915",
    "krishnakant@charcoaleats.com": "2026-01-01T12:48:48.032452",
    "mohammad.zakir@charcoaleats.com": "2026-01-01T12:48:48.032452",
    "monica.mehrotra@charcoaleats.com": "2026-01-01T12:48:48.032452",
    "rakhi@charcoaleats.com": "2026-01-01T14:45:03.571946",
    "reema.kinjalkar@charcoaleats.com": "2026-01-01T14:45:03.571946",
    "rohan@charcoaleats.com": "2026-01-01T14:45:03.571946",
    "shani.mandal@charcoaleats.com": "2026-01-01T19:39:40.898613",
    "shirish.pai@charcoaleats.com": "2026-01-01T19:39:40.898613",
    "shubham.arora@charcoaleats.com": "2026-01-01T20:46:33.523768",
    "amar.singh@charcoaleats.com": "2026-01-01T13:34:24.921939",
    "anupam.pandey@charcoaleats.com": "2026-01-01T17:21:42.465353",
    "anurag@charcoaleats.com": "2026-01-01T17:21:42.465353",
    "prabhudeen.sahani@charcoaleats.com": "2025-06-25T18:54:29.969580",
    "prashant.paradkar@charcoaleats.com": "2026-01-01T13:34:24.921939",
    "qualityassurance@charcoaleats.com": "2026-01-01T13:34:24.921939",
    "sonawaneabhishek75128@gmail.com": "2026-01-01T20:46:33.523768",
    "vikas.gupta@charcoaleats.com": "2026-01-01T20:46:33.523768",
    "desai06neel@gmail.com": "2026-01-01T17:43:44.891342",
    "ganesh.sargade@charcoaleats.com": "2026-01-01T19:18:45.402867",
    "jagdish.singh@charcoaleats.com": "2026-01-01T19:18:45.402867",
    "rohit.mehta@charcoaleats.com": "2026-01-01T23:22:20.408205",
    "rohit@charcoaleats.com": "2026-01-01T23:22:20.408205",
    "server.charcoaleats@gmail.com": "2026-01-01T21:41:31.130584",
    "pritesh.gaikwad@charcoaleats.com": "2026-01-01T19:18:45.402867",
    "gulsaz.charcoaleats@gmail.com": "2026-01-01T21:21:15.681606",
    "mansi.charcoaleats@gmail.com": "2026-01-01T21:21:15.681606",
    "namrata.bburger@gmail.com": "2026-01-01T22:22:17.810738",
    "snehal.charcoaleats@gmail.com": "2026-01-01T22:44:53.899296",
    "sufiyan.charcoaleats@gmail.com": "2026-01-01T22:44:53.899296",
    "taslimkhancharcoaleats@gmail.com": "2026-01-01T23:42:01.313877",
    "needashaikhcharcoaleats@gmail.com": "2026-01-01T22:22:17.810738",
    "nisha.charcoaleats@gmail.com": "2026-01-01T22:22:17.810738",
    "sadiyakhancharcoaleats@gmail.com": "2026-01-01T22:44:53.899296",
    "events@charcoaleats.com": "2025-12-31T16:29:07.895737",
    "sanjivani.kamble3006@gail.com": "2025-06-27T14:42:47.951518",
    "sanjivani.kamble@gmail.com": "2025-12-30T21:21:44.465236",
    "sanjivani.kamble3006@gmail.com": "2025-12-30T19:38:50.520973",
    "abhishek.rapol@charcoaleats.com": "2025-12-30T14:23:58.745675",
    "krishna.kumar@charcoaleats.com": "2025-12-30T21:21:44.465236",
    "smit.mahadik@charcoaleats.com": "2025-12-30T19:38:50.520973",
    "sudarshan.gupta@charcoaleats.com": "2025-12-30T19:38:50.520973",
    "dilip.kumar@charcoaleats.com": "2025-12-30T22:44:45.408879",
    "kanhaiya.yadav@charcoaleats.com": "2025-12-30T22:44:45.408879",
    "sagar.gupta@charcoaleats.com": "2025-12-30T21:21:44.465236",
    "andherieast.charcoaleats@gmail.com": "2026-01-01T23:22:20.408205",
    "charcoaleatslms+andherieast@gmail.com": "2026-01-01T23:42:01.313877",
    "charcoaleatslms+airoli@gmail.com": "2025-12-30T04:40:56.769805",
    "charcoaleatslms+alpha1noida@gmail.com": "2025-12-30T04:40:56.769805",
    "charcoaleatslms+badlapur@gmail.com": "2025-12-30T04:40:56.769805",
    "charcoaleatslms+baner@gmail.com": "2025-12-30T05:47:16.649996",
    "charcoaleatslms+bhandup@gmail.com": "2025-12-30T05:47:16.649996",
    "charcoaleatslms+bhosari@gmail.com": "2025-12-30T07:25:12.703148",
    "charcoaleatslms+dadar@gmail.com": "2025-12-30T07:25:12.703148",
    "charcoaleatslms+dahisar@gmail.com": "2025-12-30T07:25:12.703148",
    "charcoaleatslms+dlfphase5@gmail.com": "2025-12-30T05:47:16.649996",
    "charcoaleatslms+gaurcity@gmail.com": "2025-12-30T08:32:34.538811",
    "charcoaleatslms+ghorpadi@gmail.com": "2025-12-30T08:32:34.538811",
    "charcoaleatslms+goregaon@gmail.com": "2025-12-30T08:32:34.538811",
    "charcoaleatslms+indirapuram@gmail.com": "2025-12-30T10:27:06.672697",
    "charcoaleatslms+janakpuri@gmail.com": "2025-12-30T10:27:06.672697",
    "charcoaleatslms+jharsa@gmail.com": "2025-12-30T10:27:06.672697",
    "charcoaleatslms+kadirpur@gmail.com": "2025-12-30T09:28:08.950127",
    "charcoaleatslms+kalamboli@gmail.com": "2025-12-30T09:28:08.950127",
    "charcoaleatslms+kalina@gmail.com": "2025-12-30T09:28:08.950127",
    "charcoaleatslms+karolbagh@gmail.com": "2025-12-30T10:49:30.781767",
    "charcoaleatslms+kasarvadavli@gmail.com": "2025-12-30T10:49:30.781767",
    "charcoaleatslms+katraj@gmail.com": "2025-12-30T10:49:30.781767",
    "charcoaleatslms+kheradewatroad@gmail.com": "2025-12-30T13:38:01.509022",
    "charcoaleatslms+kothrud@gmail.com": "2025-12-30T13:38:01.509022",
    "charcoaleatslms+laxminagar@gmail.com": "2025-12-30T13:38:01.509022",
    "charcoaleatslms+lowerparel@gmail.com": "2025-12-30T11:41:13.674634",
    "charcoaleatslms+mahipalpur@gmail.com": "2025-12-30T11:41:13.674634",
    "charcoaleatslms+majiwada@gmail.com": "2025-12-30T11:41:13.674634",
    "charcoaleatslms+miraroad@gmail.com": "2025-12-30T12:50:05.736581",
    "charcoaleatslms+mukherjeenagar@gmail.com": "2025-12-30T12:50:05.736581",
    "charcoaleatslms+najafgarh@gmail.com": "2025-12-30T12:50:05.736581",
    "charcoaleatslms+nerul@gmail.com": "2025-12-30T14:23:58.745675",
    "charcoaleatslms+oshiwara@gmail.com": "2025-12-30T14:23:58.745675",
    "charcoaleatslms+palamvihar@gmail.com": "2025-12-30T16:30:23.628835",
    "charcoaleatslms+phurusungi@gmail.com": "2025-12-30T14:46:55.728049",
    "charcoaleatslms+pimplesaudagarnew@gmail.com": "2025-12-30T14:46:55.728049",
    "charcoaleatslms+pitampura@gmail.com": "2025-12-30T14:46:55.728049",
    "charcoaleatslms+rohini24@gmail.com": "2025-12-30T16:30:23.628835",
    "charcoaleatslms+sakivihar@gmail.com": "2025-12-30T16:30:23.628835",
    "charcoaleatslms+salunkhevihar@gmail.com": "2025-12-30T20:45:41.468524",
    "charcoaleatslms+sector27noida@gmail.com": "2025-12-30T21:41:40.172185",
    "charcoaleatslms+sector49noida@gmail.com": "2025-12-30T21:41:40.172185",
    "charcoaleatslms+sector66noida@gmail.com": "2025-12-30T23:21:23.498956",
    "charcoaleatslms+shivajinagar@gmail.com": "2025-12-30T18:35:27.379192",
    "charcoaleatslms+southcity2@gmail.com": "2025-12-30T18:35:27.379192",
    "charcoaleatslms+talegaon@gmail.com": "2025-12-30T18:35:27.379192",
    "charcoaleatslms+vasai@gmail.com": "2025-12-30T22:21:55.748578",
    "charcoaleatslms+vashi@gmail.com": "2025-12-30T22:21:55.748578",
    "charcoaleatslms+versova@gmail.com": "2025-12-30T22:44:45.408879",
    "charcoaleatslms+chembur@gmail.com": "2025-12-30T15:25:45.592775",
    "charcoaleatslms+dombivali@gmail.com": "2025-12-30T15:25:45.592775",
    "charcoaleatslms+dwarka@gmail.com": "2025-12-30T15:25:45.592775",
    "charcoaleatslms+hinjewadiphase3@gmail.com": "2025-12-30T17:22:49.710396",
    "charcoaleatslms+kalyan@gmail.com": "2025-12-30T17:22:49.710396",
    "charcoaleatslms+kandivalieast@gmail.com": "2025-12-30T17:22:49.710396",
    "charcoaleatslms+maladwest@gmail.com": "2025-12-30T19:18:25.379156",
    "charcoaleatslms+mayurvihar@gmail.com": "2025-12-30T19:18:25.379156",
    "charcoaleatslms+mazgaon@gmail.com": "2025-12-30T19:18:25.379156",
    "charcoaleatslms+palavacity@gmail.com": "2025-12-30T20:26:21.077716",
    "charcoaleatslms+panvel@gmail.com": "2025-12-30T20:26:21.077716",
    "charcoaleatslms+paschimvihar@gmail.com": "2025-12-30T20:26:21.077716",
    "charcoaleatslms+samatanagar@gmail.com": "2025-12-30T20:45:41.468524",
    "charcoaleatslms+sanjaynagar@gmail.com": "2025-12-30T20:45:41.468524",
    "charcoaleatslms+sector130@gmail.com": "2025-12-30T21:41:40.172185",
    "charcoaleatslms+taloja@gmail.com": "2025-12-30T23:21:23.498956",
    "charcoaleatslms+ulwe@gmail.com": "2025-12-30T23:21:23.498956",
    "charcoaleatslms+upperthane@gmail.com": "2025-12-30T22:21:55.748578",
    "charcoaleatslms+elpro@gmail.com": "2025-12-31T11:40:18.672829",
    "charcoaleatslms+heerapanna@gmail.com": "2025-12-31T11:40:18.672829",
    "charcoaleatslms+hinjewadi@gmail.com": "2025-12-31T11:40:18.672829",
    "charcoaleatslms+nallasoparaeast@gmail.com": "2025-12-31T14:22:27.186911",
    "charcoaleatslms+nanded@gmail.com": "2025-12-31T14:22:27.186911",
    "charcoaleatslms+nathupura@gmail.com": "2025-12-31T14:22:27.186911",
    "charcoaleatslms+sector85@gmail.com": "2025-12-31T14:45:13.250816",
    "charcoaleatslms+sector86noida@gmail.com": "2025-12-31T14:45:13.250816",
    "charcoaleatslms+shahpurjat@gmail.com": "2025-12-31T14:45:13.250816",
    "charcoaleatslms+badshahpur@gmail.com": "2025-12-31T09:48:11.413894",
    "charcoaleatslms+borivali@gmail.com": "2025-12-31T09:48:11.413894",
    "charcoaleatslms+charkop@gmail.com": "2025-12-31T09:48:11.413894",
    "charcoaleatslms+ramjimarket@gmail.com": "2025-12-31T11:21:02.482611",
    "charcoaleatslms+ravet@gmail.com": "2025-12-31T11:21:02.482611",
    "charcoaleatslms+rohini15@gmail.com": "2025-12-31T11:21:02.482611",
    "charcoaleatslms+khar@gmail.com": "2025-12-31T10:24:46.916800",
    "charcoaleatslms+kharadi@gmail.com": "2025-12-31T10:24:46.916800",
    "charcoaleatslms+kharghar@gmail.com": "2025-12-31T10:24:46.916800",
    "charcoaleatslms+vidyavihar@gmail.com": "2025-12-31T12:48:56.466089",
    "charcoaleatslms+virar@gmail.com": "2025-12-31T12:48:56.466089",
    "charcoaleatslms+vishrantwadi@gmail.com": "2025-12-31T12:48:56.466089",
    "anjulsahu@gmail.com": "2026-01-01T17:21:42.465353",
    "rakhi3009@gmail.com": "2026-01-01T19:39:40.898613",
    "modi.aditya9@gmail.com": "2025-12-31T16:29:07.895737",
    "eat@gmail.com": "2026-01-01T21:21:15.681606",
    "pppal1996@gmail.com": "2025-12-30T15:45:19.296584",
    "vikasshaky641@gmail.com": "2025-12-30T17:45:36.732831"
  }
}